CHANGES.rst
MANIFEST.in
README.rst
setup.cfg
setup.py
docs/INSTALL.txt
docs/LICENSE.txt
src/experimental/__init__.py
src/experimental.noacquisition.egg-info/PKG-INFO
src/experimental.noacquisition.egg-info/SOURCES.txt
src/experimental.noacquisition.egg-info/dependency_links.txt
src/experimental.noacquisition.egg-info/entry_points.txt
src/experimental.noacquisition.egg-info/namespace_packages.txt
src/experimental.noacquisition.egg-info/not-zip-safe
src/experimental.noacquisition.egg-info/requires.txt
src/experimental.noacquisition.egg-info/top_level.txt
src/experimental/noacquisition/__init__.py
src/experimental/noacquisition/config.py
src/experimental/noacquisition/configure.zcml
src/experimental/noacquisition/monkey.py
src/experimental/noacquisition/monkey_at.py
src/experimental/noacquisition/testing.py
src/experimental/noacquisition/testing.zcml
src/experimental/noacquisition/tests/__init__.py
src/experimental/noacquisition/tests/image.gif
src/experimental/noacquisition/tests/test_bad_acquisition.py