Metadata-Version: 2.1
Name: experimental.noacquisition
Version: 1.0.0b5
Summary: No acquistion during publish traverse
Home-page: http://pypi.org/pypi/collective/experimental.noacquisition
Author: Mauro Amico
Author-email: mauro.amico@gmail.com
License: BSD
Keywords: monkeypatch traverse
Platform: UNKNOWN
Classifier: Framework :: Plone
Classifier: Framework :: Zope2
Classifier: Programming Language :: Python
Provides-Extra: test
